bv/__init__.py
bv/__main__.py
bv/cli.py
bv/auth/__init__.py
bv/auth/context.py
bv/auth/login.py
bv/common/__init__.py
bv/common/url_resolver.py
bv/entrypoints/__init__.py
bv/entrypoints/registry.py
bv/orchestrator/__init__.py
bv/orchestrator/assets.py
bv/orchestrator/client.py
bv/orchestrator/queues.py
bv/packaging/__init__.py
bv/packaging/builder.py
bv/packaging/bvpackage_validator.py
bv/project/__init__.py
bv/project/config.py
bv/project/orchestrator.py
bv/runtime/__init__.py
bv/runtime/_guard.py
bv/runtime/assets.py
bv/runtime/context.py
bv/runtime/logging.py
bv/runtime/queues.py
bv/services/__init__.py
bv/services/commands.py
bv/tools/lock_generator.py
bv/validators/project_validator.py
bv/venv/__init__.py
bv/venv/manager.py
bv_sdk_cli-0.2.6.dist-info/METADATA
bv_sdk_cli-0.2.6.dist-info/WHEEL
bv_sdk_cli-0.2.6.dist-info/entry_points.txt
bv_sdk_cli-0.2.6.dist-info/RECORD
