Metadata-Version: 2.4
Name: bv-sdk-cli
Version: 0.2.6
Summary: CLI for the Bot Velocity RPA & Agentic Platform
Author: Bot Velocity Team
License: Proprietary
Keywords: agentic,bot-velocity,cli,rpa
Requires-Python: >=3.10
Requires-Dist: bv-runtime>=0.2.6
Requires-Dist: pyyaml>=6.0
Requires-Dist: requests>=2.32
Requires-Dist: typer>=0.12
Provides-Extra: dev
Requires-Dist: pytest>=8.0; extra == 'dev'
